<scenario>
    <at t="0">
        <set-channel-param src-module="client[0]" src-gate="pppg$o[0]" par="delay" value="27.25ms"/>
        <set-channel-param src-module="router1" src-gate="pppg$o[0]" par="delay" value="27.25ms"/>

        <set-channel-param src-module="server[0]" src-gate="pppg$o[0]" par="delay" value="27.25ms"/>
        <set-channel-param src-module="router2" src-gate="pppg$o[0]" par="delay" value="27.25ms"/>

        <set-channel-param src-module="router1" src-gate="pppg$o[1]" par="datarate" value="50Mbps"/>
        <set-channel-param src-module="router2" src-gate="pppg$o[1]" par="datarate" value="50Mbps"/>
    </at>
    <at t="10">
        <set-channel-param src-module="client[0]" src-gate="pppg$o[0]" par="delay" value="9.0ms"/>
        <set-channel-param src-module="router1" src-gate="pppg$o[0]" par="delay" value="9.0ms"/>

        <set-channel-param src-module="server[0]" src-gate="pppg$o[0]" par="delay" value="9.0ms"/>
        <set-channel-param src-module="router2" src-gate="pppg$o[0]" par="delay" value="9.0ms"/>

        <set-channel-param src-module="router1" src-gate="pppg$o[1]" par="datarate" value="85Mbps"/>
        <set-channel-param src-module="router2" src-gate="pppg$o[1]" par="datarate" value="85Mbps"/>
        <set-channel-param src-module="router1" src-gate="pppg$o[1]" par="per" value="0.007543765295798113"/>
    </at>
    <at t="25">
        <set-channel-param src-module="client[0]" src-gate="pppg$o[0]" par="delay" value="2.75ms"/>
        <set-channel-param src-module="router1" src-gate="pppg$o[0]" par="delay" value="2.75ms"/>

        <set-channel-param src-module="server[0]" src-gate="pppg$o[0]" par="delay" value="2.75ms"/>
        <set-channel-param src-module="router2" src-gate="pppg$o[0]" par="delay" value="2.75ms"/>

        <set-channel-param src-module="router1" src-gate="pppg$o[1]" par="datarate" value="69Mbps"/>
        <set-channel-param src-module="router2" src-gate="pppg$o[1]" par="datarate" value="69Mbps"/>
        <set-channel-param src-module="router1" src-gate="pppg$o[1]" par="per" value="0.004556803773207893"/>
    </at>
    <at t="40">
        <set-channel-param src-module="client[0]" src-gate="pppg$o[0]" par="delay" value="5.0ms"/>
        <set-channel-param src-module="router1" src-gate="pppg$o[0]" par="delay" value="5.0ms"/>

        <set-channel-param src-module="server[0]" src-gate="pppg$o[0]" par="delay" value="5.0ms"/>
        <set-channel-param src-module="router2" src-gate="pppg$o[0]" par="delay" value="5.0ms"/>

        <set-channel-param src-module="router1" src-gate="pppg$o[1]" par="datarate" value="52Mbps"/>
        <set-channel-param src-module="router2" src-gate="pppg$o[1]" par="datarate" value="52Mbps"/>
        <set-channel-param src-module="router1" src-gate="pppg$o[1]" par="per" value="0.00998943741453251"/>
    </at>
    <at t="55">
        <set-channel-param src-module="client[0]" src-gate="pppg$o[0]" par="delay" value="4.0ms"/>
        <set-channel-param src-module="router1" src-gate="pppg$o[0]" par="delay" value="4.0ms"/>

        <set-channel-param src-module="server[0]" src-gate="pppg$o[0]" par="delay" value="4.0ms"/>
        <set-channel-param src-module="router2" src-gate="pppg$o[0]" par="delay" value="4.0ms"/>

        <set-channel-param src-module="router1" src-gate="pppg$o[1]" par="datarate" value="66Mbps"/>
        <set-channel-param src-module="router2" src-gate="pppg$o[1]" par="datarate" value="66Mbps"/>
        <set-channel-param src-module="router1" src-gate="pppg$o[1]" par="per" value="0.007907273789287678"/>
    </at>
    <at t="70">
        <set-channel-param src-module="client[0]" src-gate="pppg$o[0]" par="delay" value="14.5ms"/>
        <set-channel-param src-module="router1" src-gate="pppg$o[0]" par="delay" value="14.5ms"/>

        <set-channel-param src-module="server[0]" src-gate="pppg$o[0]" par="delay" value="14.5ms"/>
        <set-channel-param src-module="router2" src-gate="pppg$o[0]" par="delay" value="14.5ms"/>

        <set-channel-param src-module="router1" src-gate="pppg$o[1]" par="datarate" value="98Mbps"/>
        <set-channel-param src-module="router2" src-gate="pppg$o[1]" par="datarate" value="98Mbps"/>
        <set-channel-param src-module="router1" src-gate="pppg$o[1]" par="per" value="0.007738748636452434"/>
    </at>
    <at t="85">
        <set-channel-param src-module="client[0]" src-gate="pppg$o[0]" par="delay" value="9.25ms"/>
        <set-channel-param src-module="router1" src-gate="pppg$o[0]" par="delay" value="9.25ms"/>

        <set-channel-param src-module="server[0]" src-gate="pppg$o[0]" par="delay" value="9.25ms"/>
        <set-channel-param src-module="router2" src-gate="pppg$o[0]" par="delay" value="9.25ms"/>

        <set-channel-param src-module="router1" src-gate="pppg$o[1]" par="datarate" value="61Mbps"/>
        <set-channel-param src-module="router2" src-gate="pppg$o[1]" par="datarate" value="61Mbps"/>
        <set-channel-param src-module="router1" src-gate="pppg$o[1]" par="per" value="0.008121931575279868"/>
    </at>
    <at t="100">
        <set-channel-param src-module="client[0]" src-gate="pppg$o[0]" par="delay" value="17.5ms"/>
        <set-channel-param src-module="router1" src-gate="pppg$o[0]" par="delay" value="17.5ms"/>

        <set-channel-param src-module="server[0]" src-gate="pppg$o[0]" par="delay" value="17.5ms"/>
        <set-channel-param src-module="router2" src-gate="pppg$o[0]" par="delay" value="17.5ms"/>

        <set-channel-param src-module="router1" src-gate="pppg$o[1]" par="datarate" value="76Mbps"/>
        <set-channel-param src-module="router2" src-gate="pppg$o[1]" par="datarate" value="76Mbps"/>
        <set-channel-param src-module="router1" src-gate="pppg$o[1]" par="per" value="0.004586015759114453"/>
    </at>
    <at t="115">
        <set-channel-param src-module="client[0]" src-gate="pppg$o[0]" par="delay" value="23.75ms"/>
        <set-channel-param src-module="router1" src-gate="pppg$o[0]" par="delay" value="23.75ms"/>

        <set-channel-param src-module="server[0]" src-gate="pppg$o[0]" par="delay" value="23.75ms"/>
        <set-channel-param src-module="router2" src-gate="pppg$o[0]" par="delay" value="23.75ms"/>

        <set-channel-param src-module="router1" src-gate="pppg$o[1]" par="datarate" value="97Mbps"/>
        <set-channel-param src-module="router2" src-gate="pppg$o[1]" par="datarate" value="97Mbps"/>
        <set-channel-param src-module="router1" src-gate="pppg$o[1]" par="per" value="0.006903257430513934"/>
    </at>
    <at t="130">
        <set-channel-param src-module="client[0]" src-gate="pppg$o[0]" par="delay" value="18.5ms"/>
        <set-channel-param src-module="router1" src-gate="pppg$o[0]" par="delay" value="18.5ms"/>

        <set-channel-param src-module="server[0]" src-gate="pppg$o[0]" par="delay" value="18.5ms"/>
        <set-channel-param src-module="router2" src-gate="pppg$o[0]" par="delay" value="18.5ms"/>

        <set-channel-param src-module="router1" src-gate="pppg$o[1]" par="datarate" value="54Mbps"/>
        <set-channel-param src-module="router2" src-gate="pppg$o[1]" par="datarate" value="54Mbps"/>
        <set-channel-param src-module="router1" src-gate="pppg$o[1]" par="per" value="0.008391410060215033"/>
    </at>
    <at t="145">
        <set-channel-param src-module="client[0]" src-gate="pppg$o[0]" par="delay" value="24.0ms"/>
        <set-channel-param src-module="router1" src-gate="pppg$o[0]" par="delay" value="24.0ms"/>

        <set-channel-param src-module="server[0]" src-gate="pppg$o[0]" par="delay" value="24.0ms"/>
        <set-channel-param src-module="router2" src-gate="pppg$o[0]" par="delay" value="24.0ms"/>

        <set-channel-param src-module="router1" src-gate="pppg$o[1]" par="datarate" value="90Mbps"/>
        <set-channel-param src-module="router2" src-gate="pppg$o[1]" par="datarate" value="90Mbps"/>
        <set-channel-param src-module="router1" src-gate="pppg$o[1]" par="per" value="0.002170433140266751"/>
    </at>
    <at t="160">
        <set-channel-param src-module="client[0]" src-gate="pppg$o[0]" par="delay" value="11.75ms"/>
        <set-channel-param src-module="router1" src-gate="pppg$o[0]" par="delay" value="11.75ms"/>

        <set-channel-param src-module="server[0]" src-gate="pppg$o[0]" par="delay" value="11.75ms"/>
        <set-channel-param src-module="router2" src-gate="pppg$o[0]" par="delay" value="11.75ms"/>

        <set-channel-param src-module="router1" src-gate="pppg$o[1]" par="datarate" value="74Mbps"/>
        <set-channel-param src-module="router2" src-gate="pppg$o[1]" par="datarate" value="74Mbps"/>
        <set-channel-param src-module="router1" src-gate="pppg$o[1]" par="per" value="0.009198915194289559"/>
    </at>
    <at t="175">
        <set-channel-param src-module="client[0]" src-gate="pppg$o[0]" par="delay" value="13.5ms"/>
        <set-channel-param src-module="router1" src-gate="pppg$o[0]" par="delay" value="13.5ms"/>

        <set-channel-param src-module="server[0]" src-gate="pppg$o[0]" par="delay" value="13.5ms"/>
        <set-channel-param src-module="router2" src-gate="pppg$o[0]" par="delay" value="13.5ms"/>

        <set-channel-param src-module="router1" src-gate="pppg$o[1]" par="datarate" value="92Mbps"/>
        <set-channel-param src-module="router2" src-gate="pppg$o[1]" par="datarate" value="92Mbps"/>
        <set-channel-param src-module="router1" src-gate="pppg$o[1]" par="per" value="0.0018091871569418173"/>
    </at>
    <at t="190">
        <set-channel-param src-module="client[0]" src-gate="pppg$o[0]" par="delay" value="8.5ms"/>
        <set-channel-param src-module="router1" src-gate="pppg$o[0]" par="delay" value="8.5ms"/>

        <set-channel-param src-module="server[0]" src-gate="pppg$o[0]" par="delay" value="8.5ms"/>
        <set-channel-param src-module="router2" src-gate="pppg$o[0]" par="delay" value="8.5ms"/>

        <set-channel-param src-module="router1" src-gate="pppg$o[1]" par="datarate" value="82Mbps"/>
        <set-channel-param src-module="router2" src-gate="pppg$o[1]" par="datarate" value="82Mbps"/>
        <set-channel-param src-module="router1" src-gate="pppg$o[1]" par="per" value="0.0007300339146780987"/>
    </at>
    <at t="205">
        <set-channel-param src-module="client[0]" src-gate="pppg$o[0]" par="delay" value="18.0ms"/>
        <set-channel-param src-module="router1" src-gate="pppg$o[0]" par="delay" value="18.0ms"/>

        <set-channel-param src-module="server[0]" src-gate="pppg$o[0]" par="delay" value="18.0ms"/>
        <set-channel-param src-module="router2" src-gate="pppg$o[0]" par="delay" value="18.0ms"/>

        <set-channel-param src-module="router1" src-gate="pppg$o[1]" par="datarate" value="78Mbps"/>
        <set-channel-param src-module="router2" src-gate="pppg$o[1]" par="datarate" value="78Mbps"/>
        <set-channel-param src-module="router1" src-gate="pppg$o[1]" par="per" value="0.0067971959611562195"/>
    </at>
    <at t="220">
        <set-channel-param src-module="client[0]" src-gate="pppg$o[0]" par="delay" value="20.0ms"/>
        <set-channel-param src-module="router1" src-gate="pppg$o[0]" par="delay" value="20.0ms"/>

        <set-channel-param src-module="server[0]" src-gate="pppg$o[0]" par="delay" value="20.0ms"/>
        <set-channel-param src-module="router2" src-gate="pppg$o[0]" par="delay" value="20.0ms"/>

        <set-channel-param src-module="router1" src-gate="pppg$o[1]" par="datarate" value="93Mbps"/>
        <set-channel-param src-module="router2" src-gate="pppg$o[1]" par="datarate" value="93Mbps"/>
        <set-channel-param src-module="router1" src-gate="pppg$o[1]" par="per" value="0.009708968505529198"/>
    </at>
    <at t="235">
        <set-channel-param src-module="client[0]" src-gate="pppg$o[0]" par="delay" value="6.5ms"/>
        <set-channel-param src-module="router1" src-gate="pppg$o[0]" par="delay" value="6.5ms"/>

        <set-channel-param src-module="server[0]" src-gate="pppg$o[0]" par="delay" value="6.5ms"/>
        <set-channel-param src-module="router2" src-gate="pppg$o[0]" par="delay" value="6.5ms"/>

        <set-channel-param src-module="router1" src-gate="pppg$o[1]" par="datarate" value="59Mbps"/>
        <set-channel-param src-module="router2" src-gate="pppg$o[1]" par="datarate" value="59Mbps"/>
        <set-channel-param src-module="router1" src-gate="pppg$o[1]" par="per" value="0.003640083877671594"/>
    </at>
    <at t="250">
        <set-channel-param src-module="client[0]" src-gate="pppg$o[0]" par="delay" value="3.75ms"/>
        <set-channel-param src-module="router1" src-gate="pppg$o[0]" par="delay" value="3.75ms"/>

        <set-channel-param src-module="server[0]" src-gate="pppg$o[0]" par="delay" value="3.75ms"/>
        <set-channel-param src-module="router2" src-gate="pppg$o[0]" par="delay" value="3.75ms"/>

        <set-channel-param src-module="router1" src-gate="pppg$o[1]" par="datarate" value="71Mbps"/>
        <set-channel-param src-module="router2" src-gate="pppg$o[1]" par="datarate" value="71Mbps"/>
        <set-channel-param src-module="router1" src-gate="pppg$o[1]" par="per" value="0.0036927021914191283"/>
    </at>
    <at t="265">
        <set-channel-param src-module="client[0]" src-gate="pppg$o[0]" par="delay" value="16.25ms"/>
        <set-channel-param src-module="router1" src-gate="pppg$o[0]" par="delay" value="16.25ms"/>

        <set-channel-param src-module="server[0]" src-gate="pppg$o[0]" par="delay" value="16.25ms"/>
        <set-channel-param src-module="router2" src-gate="pppg$o[0]" par="delay" value="16.25ms"/>

        <set-channel-param src-module="router1" src-gate="pppg$o[1]" par="datarate" value="89Mbps"/>
        <set-channel-param src-module="router2" src-gate="pppg$o[1]" par="datarate" value="89Mbps"/>
        <set-channel-param src-module="router1" src-gate="pppg$o[1]" par="per" value="0.007907391683360897"/>
    </at>
    <at t="280">
        <set-channel-param src-module="client[0]" src-gate="pppg$o[0]" par="delay" value="22.25ms"/>
        <set-channel-param src-module="router1" src-gate="pppg$o[0]" par="delay" value="22.25ms"/>

        <set-channel-param src-module="server[0]" src-gate="pppg$o[0]" par="delay" value="22.25ms"/>
        <set-channel-param src-module="router2" src-gate="pppg$o[0]" par="delay" value="22.25ms"/>

        <set-channel-param src-module="router1" src-gate="pppg$o[1]" par="datarate" value="56Mbps"/>
        <set-channel-param src-module="router2" src-gate="pppg$o[1]" par="datarate" value="56Mbps"/>
        <set-channel-param src-module="router1" src-gate="pppg$o[1]" par="per" value="0.008070379161917695"/>
    </at>
    <at t="295">
        <set-channel-param src-module="client[0]" src-gate="pppg$o[0]" par="delay" value="2.25ms"/>
        <set-channel-param src-module="router1" src-gate="pppg$o[0]" par="delay" value="2.25ms"/>

        <set-channel-param src-module="server[0]" src-gate="pppg$o[0]" par="delay" value="2.25ms"/>
        <set-channel-param src-module="router2" src-gate="pppg$o[0]" par="delay" value="2.25ms"/>

        <set-channel-param src-module="router1" src-gate="pppg$o[1]" par="datarate" value="65Mbps"/>
        <set-channel-param src-module="router2" src-gate="pppg$o[1]" par="datarate" value="65Mbps"/>
        <set-channel-param src-module="router1" src-gate="pppg$o[1]" par="per" value="0.005741569115139154"/>
    </at>
</scenario>