{
                     "0": 78,
                     "15": 38,
                     "30": 89,
                     "45": 99,
                     "60": 7,
                     "75": 98,
                     "90": 74,
                     "105": 77,
                     "120": 38,
                     "135": 92,
                     "150": 47,
                     "165": 57,
                     "180": 94,
                     "195": 94,
                     "210": 17,
                     "225": 30,
                     "240": 67,
                     "255": 70,
                     "270": 69,
                     "285": 86,
                     "300": 60
}