{
                     "0": 65,
                     "15": 34,
                     "30": 89,
                     "45": 86,
                     "60": 43,
                     "75": 23,
                     "90": 44,
                     "105": 82,
                     "120": 82,
                     "135": 64,
                     "150": 95,
                     "165": 44,
                     "180": 16,
                     "195": 71,
                     "210": 42,
                     "225": 15,
                     "240": 5,
                     "255": 67,
                     "270": 45,
                     "285": 26,
                     "300": 6
}