<scenario>
    <at t="0">
        <set-channel-param src-module="client[0]" src-gate="pppg$o[0]" par="delay" value="2.0ms"/>
        <set-channel-param src-module="router1" src-gate="pppg$o[0]" par="delay" value="2.0ms"/>

        <set-channel-param src-module="server[0]" src-gate="pppg$o[0]" par="delay" value="2.0ms"/>
        <set-channel-param src-module="router2" src-gate="pppg$o[0]" par="delay" value="2.0ms"/>

        <set-channel-param src-module="router1" src-gate="pppg$o[1]" par="datarate" value="86Mbps"/>
        <set-channel-param src-module="router2" src-gate="pppg$o[1]" par="datarate" value="86Mbps"/>
        <set-channel-param src-module="router1" src-gate="pppg$o[1]" par="per" value="0.0043"/>
    </at>
    <at t="15">
        <set-channel-param src-module="client[0]" src-gate="pppg$o[0]" par="delay" value="1.25ms"/>
        <set-channel-param src-module="router1" src-gate="pppg$o[0]" par="delay" value="1.25ms"/>

        <set-channel-param src-module="server[0]" src-gate="pppg$o[0]" par="delay" value="1.25ms"/>
        <set-channel-param src-module="router2" src-gate="pppg$o[0]" par="delay" value="1.25ms"/>

        <set-channel-param src-module="router1" src-gate="pppg$o[1]" par="datarate" value="86Mbps"/>
        <set-channel-param src-module="router2" src-gate="pppg$o[1]" par="datarate" value="86Mbps"/>
        <set-channel-param src-module="router1" src-gate="pppg$o[1]" par="per" value="0.0021"/>
    </at>
    <at t="30">
        <set-channel-param src-module="client[0]" src-gate="pppg$o[0]" par="delay" value="9.75ms"/>
        <set-channel-param src-module="router1" src-gate="pppg$o[0]" par="delay" value="9.75ms"/>

        <set-channel-param src-module="server[0]" src-gate="pppg$o[0]" par="delay" value="9.75ms"/>
        <set-channel-param src-module="router2" src-gate="pppg$o[0]" par="delay" value="9.75ms"/>

        <set-channel-param src-module="router1" src-gate="pppg$o[1]" par="datarate" value="81Mbps"/>
        <set-channel-param src-module="router2" src-gate="pppg$o[1]" par="datarate" value="81Mbps"/>
        <set-channel-param src-module="router1" src-gate="pppg$o[1]" par="per" value="0.0065"/>
    </at>
    <at t="45">
        <set-channel-param src-module="client[0]" src-gate="pppg$o[0]" par="delay" value="2.0ms"/>
        <set-channel-param src-module="router1" src-gate="pppg$o[0]" par="delay" value="2.0ms"/>

        <set-channel-param src-module="server[0]" src-gate="pppg$o[0]" par="delay" value="2.0ms"/>
        <set-channel-param src-module="router2" src-gate="pppg$o[0]" par="delay" value="2.0ms"/>

        <set-channel-param src-module="router1" src-gate="pppg$o[1]" par="datarate" value="60Mbps"/>
        <set-channel-param src-module="router2" src-gate="pppg$o[1]" par="datarate" value="60Mbps"/>
        <set-channel-param src-module="router1" src-gate="pppg$o[1]" par="per" value="0.0052"/>
    </at>
    <at t="60">
        <set-channel-param src-module="client[0]" src-gate="pppg$o[0]" par="delay" value="3.25ms"/>
        <set-channel-param src-module="router1" src-gate="pppg$o[0]" par="delay" value="3.25ms"/>

        <set-channel-param src-module="server[0]" src-gate="pppg$o[0]" par="delay" value="3.25ms"/>
        <set-channel-param src-module="router2" src-gate="pppg$o[0]" par="delay" value="3.25ms"/>

        <set-channel-param src-module="router1" src-gate="pppg$o[1]" par="datarate" value="70Mbps"/>
        <set-channel-param src-module="router2" src-gate="pppg$o[1]" par="datarate" value="70Mbps"/>
        <set-channel-param src-module="router1" src-gate="pppg$o[1]" par="per" value="0.0025"/>
    </at>
    <at t="75">
        <set-channel-param src-module="client[0]" src-gate="pppg$o[0]" par="delay" value="12.5ms"/>
        <set-channel-param src-module="router1" src-gate="pppg$o[0]" par="delay" value="12.5ms"/>

        <set-channel-param src-module="server[0]" src-gate="pppg$o[0]" par="delay" value="12.5ms"/>
        <set-channel-param src-module="router2" src-gate="pppg$o[0]" par="delay" value="12.5ms"/>

        <set-channel-param src-module="router1" src-gate="pppg$o[1]" par="datarate" value="97Mbps"/>
        <set-channel-param src-module="router2" src-gate="pppg$o[1]" par="datarate" value="97Mbps"/>
        <set-channel-param src-module="router1" src-gate="pppg$o[1]" par="per" value="0.0004"/>
    </at>
    <at t="90">
        <set-channel-param src-module="client[0]" src-gate="pppg$o[0]" par="delay" value="20.25ms"/>
        <set-channel-param src-module="router1" src-gate="pppg$o[0]" par="delay" value="20.25ms"/>

        <set-channel-param src-module="server[0]" src-gate="pppg$o[0]" par="delay" value="20.25ms"/>
        <set-channel-param src-module="router2" src-gate="pppg$o[0]" par="delay" value="20.25ms"/>

        <set-channel-param src-module="router1" src-gate="pppg$o[1]" par="datarate" value="58Mbps"/>
        <set-channel-param src-module="router2" src-gate="pppg$o[1]" par="datarate" value="58Mbps"/>
        <set-channel-param src-module="router1" src-gate="pppg$o[1]" par="per" value="0.0036"/>
    </at>
    <at t="105">
        <set-channel-param src-module="client[0]" src-gate="pppg$o[0]" par="delay" value="10.0ms"/>
        <set-channel-param src-module="router1" src-gate="pppg$o[0]" par="delay" value="10.0ms"/>

        <set-channel-param src-module="server[0]" src-gate="pppg$o[0]" par="delay" value="10.0ms"/>
        <set-channel-param src-module="router2" src-gate="pppg$o[0]" par="delay" value="10.0ms"/>

        <set-channel-param src-module="router1" src-gate="pppg$o[1]" par="datarate" value="76Mbps"/>
        <set-channel-param src-module="router2" src-gate="pppg$o[1]" par="datarate" value="76Mbps"/>
        <set-channel-param src-module="router1" src-gate="pppg$o[1]" par="per" value="0.0083"/>
    </at>
    <at t="120">
        <set-channel-param src-module="client[0]" src-gate="pppg$o[0]" par="delay" value="15.5ms"/>
        <set-channel-param src-module="router1" src-gate="pppg$o[0]" par="delay" value="15.5ms"/>

        <set-channel-param src-module="server[0]" src-gate="pppg$o[0]" par="delay" value="15.5ms"/>
        <set-channel-param src-module="router2" src-gate="pppg$o[0]" par="delay" value="15.5ms"/>

        <set-channel-param src-module="router1" src-gate="pppg$o[1]" par="datarate" value="66Mbps"/>
        <set-channel-param src-module="router2" src-gate="pppg$o[1]" par="datarate" value="66Mbps"/>
        <set-channel-param src-module="router1" src-gate="pppg$o[1]" par="per" value="0.0017"/>
    </at>
    <at t="135">
        <set-channel-param src-module="client[0]" src-gate="pppg$o[0]" par="delay" value="22.0ms"/>
        <set-channel-param src-module="router1" src-gate="pppg$o[0]" par="delay" value="22.0ms"/>

        <set-channel-param src-module="server[0]" src-gate="pppg$o[0]" par="delay" value="22.0ms"/>
        <set-channel-param src-module="router2" src-gate="pppg$o[0]" par="delay" value="22.0ms"/>

        <set-channel-param src-module="router1" src-gate="pppg$o[1]" par="datarate" value="69Mbps"/>
        <set-channel-param src-module="router2" src-gate="pppg$o[1]" par="datarate" value="69Mbps"/>
        <set-channel-param src-module="router1" src-gate="pppg$o[1]" par="per" value="0.0036"/>
    </at>
    <at t="150">
        <set-channel-param src-module="client[0]" src-gate="pppg$o[0]" par="delay" value="8.5ms"/>
        <set-channel-param src-module="router1" src-gate="pppg$o[0]" par="delay" value="8.5ms"/>

        <set-channel-param src-module="server[0]" src-gate="pppg$o[0]" par="delay" value="8.5ms"/>
        <set-channel-param src-module="router2" src-gate="pppg$o[0]" par="delay" value="8.5ms"/>

        <set-channel-param src-module="router1" src-gate="pppg$o[1]" par="datarate" value="79Mbps"/>
        <set-channel-param src-module="router2" src-gate="pppg$o[1]" par="datarate" value="79Mbps"/>
        <set-channel-param src-module="router1" src-gate="pppg$o[1]" par="per" value="0.0097"/>
    </at>
    <at t="165">
        <set-channel-param src-module="client[0]" src-gate="pppg$o[0]" par="delay" value="13.0ms"/>
        <set-channel-param src-module="router1" src-gate="pppg$o[0]" par="delay" value="13.0ms"/>

        <set-channel-param src-module="server[0]" src-gate="pppg$o[0]" par="delay" value="13.0ms"/>
        <set-channel-param src-module="router2" src-gate="pppg$o[0]" par="delay" value="13.0ms"/>

        <set-channel-param src-module="router1" src-gate="pppg$o[1]" par="datarate" value="89Mbps"/>
        <set-channel-param src-module="router2" src-gate="pppg$o[1]" par="datarate" value="89Mbps"/>
        <set-channel-param src-module="router1" src-gate="pppg$o[1]" par="per" value="0.0004"/>
    </at>
    <at t="180">
        <set-channel-param src-module="client[0]" src-gate="pppg$o[0]" par="delay" value="8.5ms"/>
        <set-channel-param src-module="router1" src-gate="pppg$o[0]" par="delay" value="8.5ms"/>

        <set-channel-param src-module="server[0]" src-gate="pppg$o[0]" par="delay" value="8.5ms"/>
        <set-channel-param src-module="router2" src-gate="pppg$o[0]" par="delay" value="8.5ms"/>

        <set-channel-param src-module="router1" src-gate="pppg$o[1]" par="datarate" value="50Mbps"/>
        <set-channel-param src-module="router2" src-gate="pppg$o[1]" par="datarate" value="50Mbps"/>
        <set-channel-param src-module="router1" src-gate="pppg$o[1]" par="per" value="0.0013"/>
    </at>
    <at t="195">
        <set-channel-param src-module="client[0]" src-gate="pppg$o[0]" par="delay" value="18.0ms"/>
        <set-channel-param src-module="router1" src-gate="pppg$o[0]" par="delay" value="18.0ms"/>

        <set-channel-param src-module="server[0]" src-gate="pppg$o[0]" par="delay" value="18.0ms"/>
        <set-channel-param src-module="router2" src-gate="pppg$o[0]" par="delay" value="18.0ms"/>

        <set-channel-param src-module="router1" src-gate="pppg$o[1]" par="datarate" value="69Mbps"/>
        <set-channel-param src-module="router2" src-gate="pppg$o[1]" par="datarate" value="69Mbps"/>
        <set-channel-param src-module="router1" src-gate="pppg$o[1]" par="per" value="0.0037"/>
    </at>
    <at t="210">
        <set-channel-param src-module="client[0]" src-gate="pppg$o[0]" par="delay" value="11.0ms"/>
        <set-channel-param src-module="router1" src-gate="pppg$o[0]" par="delay" value="11.0ms"/>

        <set-channel-param src-module="server[0]" src-gate="pppg$o[0]" par="delay" value="11.0ms"/>
        <set-channel-param src-module="router2" src-gate="pppg$o[0]" par="delay" value="11.0ms"/>

        <set-channel-param src-module="router1" src-gate="pppg$o[1]" par="datarate" value="65Mbps"/>
        <set-channel-param src-module="router2" src-gate="pppg$o[1]" par="datarate" value="65Mbps"/>
        <set-channel-param src-module="router1" src-gate="pppg$o[1]" par="per" value="0.0067"/>
    </at>
    <at t="225">
        <set-channel-param src-module="client[0]" src-gate="pppg$o[0]" par="delay" value="14.75ms"/>
        <set-channel-param src-module="router1" src-gate="pppg$o[0]" par="delay" value="14.75ms"/>

        <set-channel-param src-module="server[0]" src-gate="pppg$o[0]" par="delay" value="14.75ms"/>
        <set-channel-param src-module="router2" src-gate="pppg$o[0]" par="delay" value="14.75ms"/>

        <set-channel-param src-module="router1" src-gate="pppg$o[1]" par="datarate" value="78Mbps"/>
        <set-channel-param src-module="router2" src-gate="pppg$o[1]" par="datarate" value="78Mbps"/>
        <set-channel-param src-module="router1" src-gate="pppg$o[1]" par="per" value="0.0047"/>
    </at>
    <at t="240">
        <set-channel-param src-module="client[0]" src-gate="pppg$o[0]" par="delay" value="19.5ms"/>
        <set-channel-param src-module="router1" src-gate="pppg$o[0]" par="delay" value="19.5ms"/>

        <set-channel-param src-module="server[0]" src-gate="pppg$o[0]" par="delay" value="19.5ms"/>
        <set-channel-param src-module="router2" src-gate="pppg$o[0]" par="delay" value="19.5ms"/>

        <set-channel-param src-module="router1" src-gate="pppg$o[1]" par="datarate" value="91Mbps"/>
        <set-channel-param src-module="router2" src-gate="pppg$o[1]" par="datarate" value="91Mbps"/>
        <set-channel-param src-module="router1" src-gate="pppg$o[1]" par="per" value="0.0032"/>
    </at>
    <at t="255">
        <set-channel-param src-module="client[0]" src-gate="pppg$o[0]" par="delay" value="6.0ms"/>
        <set-channel-param src-module="router1" src-gate="pppg$o[0]" par="delay" value="6.0ms"/>

        <set-channel-param src-module="server[0]" src-gate="pppg$o[0]" par="delay" value="6.0ms"/>
        <set-channel-param src-module="router2" src-gate="pppg$o[0]" par="delay" value="6.0ms"/>

        <set-channel-param src-module="router1" src-gate="pppg$o[1]" par="datarate" value="82Mbps"/>
        <set-channel-param src-module="router2" src-gate="pppg$o[1]" par="datarate" value="82Mbps"/>
        <set-channel-param src-module="router1" src-gate="pppg$o[1]" par="per" value="0.0084"/>
    </at>
    <at t="270">
        <set-channel-param src-module="client[0]" src-gate="pppg$o[0]" par="delay" value="8.5ms"/>
        <set-channel-param src-module="router1" src-gate="pppg$o[0]" par="delay" value="8.5ms"/>

        <set-channel-param src-module="server[0]" src-gate="pppg$o[0]" par="delay" value="8.5ms"/>
        <set-channel-param src-module="router2" src-gate="pppg$o[0]" par="delay" value="8.5ms"/>

        <set-channel-param src-module="router1" src-gate="pppg$o[1]" par="datarate" value="76Mbps"/>
        <set-channel-param src-module="router2" src-gate="pppg$o[1]" par="datarate" value="76Mbps"/>
        <set-channel-param src-module="router1" src-gate="pppg$o[1]" par="per" value="0.0004"/>
    </at>
    <at t="285">
        <set-channel-param src-module="client[0]" src-gate="pppg$o[0]" par="delay" value="10.5ms"/>
        <set-channel-param src-module="router1" src-gate="pppg$o[0]" par="delay" value="10.5ms"/>

        <set-channel-param src-module="server[0]" src-gate="pppg$o[0]" par="delay" value="10.5ms"/>
        <set-channel-param src-module="router2" src-gate="pppg$o[0]" par="delay" value="10.5ms"/>

        <set-channel-param src-module="router1" src-gate="pppg$o[1]" par="datarate" value="81Mbps"/>
        <set-channel-param src-module="router2" src-gate="pppg$o[1]" par="datarate" value="81Mbps"/>
        <set-channel-param src-module="router1" src-gate="pppg$o[1]" par="per" value="0.0082"/>
    </at>
    <at t="300">
        <set-channel-param src-module="client[0]" src-gate="pppg$o[0]" par="delay" value="3.25ms"/>
        <set-channel-param src-module="router1" src-gate="pppg$o[0]" par="delay" value="3.25ms"/>

        <set-channel-param src-module="server[0]" src-gate="pppg$o[0]" par="delay" value="3.25ms"/>
        <set-channel-param src-module="router2" src-gate="pppg$o[0]" par="delay" value="3.25ms"/>

        <set-channel-param src-module="router1" src-gate="pppg$o[1]" par="datarate" value="92Mbps"/>
        <set-channel-param src-module="router2" src-gate="pppg$o[1]" par="datarate" value="92Mbps"/>
        <set-channel-param src-module="router1" src-gate="pppg$o[1]" par="per" value="0.0053"/>
    </at>
</scenario>